dictamen/__init__.py
dictamen/dictamen.py
dictamen/validator_rule.py
dictionary/__init__.py
jira/__init__.py
jira/api_client/__init__.py
jira/api_client/jira_api.py
jira/api_client/jira_session.py
jira/commons/__init__.py
jira/commons/constants.py
jira/model/__init__.py
jira/model/feature.py
jira/model/issue_base.py
jira/model/issue_status.py
jira/model/issue_task.py
jira/model/story.py
jira/producer/__init__.py
jira/producer/jira_producer.py
jira/utils/__init__.py
jira/utils/issue_utils.py
pysideapi-0.0.3.dist-info/LICENSE.txt
pysideapi-0.0.3.dist-info/METADATA
pysideapi-0.0.3.dist-info/WHEEL
pysideapi-0.0.3.dist-info/top_level.txt
pysideapi-0.0.3.dist-info/RECORD
